repflaskboilerplate/__init__.py
repflaskboilerplate/app_global.py
repflaskboilerplate/db.py
repflaskboilerplate-0.5.6.data/scripts/install
repflaskboilerplate-0.5.6.dist-info/METADATA
repflaskboilerplate-0.5.6.dist-info/RECORD
repflaskboilerplate-0.5.6.dist-info/WHEEL
repflaskboilerplate-0.5.6.dist-info/top_level.txt
