Metadata-Version: 2.1
Name: repflaskboilerplate
Version: 0.5.6
Summary: a SQLAlchemy helper package
Home-page: https://github.com/RyanGuild/REP-flask-boilerplate
Author: Ryan Guild
Author-email: ryanguild489@gmail.com
License: UNKNOWN
Platform: UNKNOWN
Classifier: Programming Language :: Python :: 3
Classifier: License :: OSI Approved :: MIT License
Classifier: Operating System :: OS Independent
